pyneople/__init__.py
pyneople/api_to_mongo.py
pyneople/mongo_to_psql.py
pyneople/api/METADATA.py
pyneople/api/__init__.py
pyneople/api/api_processors.py
pyneople/api/endpoint_mapping.py
pyneople/api/endpoints.py
pyneople/api/parser.py
pyneople/api/seeder.py
pyneople/api/url_builder.py
pyneople/config/__init__.py
pyneople/config/config.py
pyneople/db/query/character_timelines.sql
pyneople/db/query/characters.sql
pyneople/db/schema/main_tables/create_character_timelines.sql
pyneople/db/schema/main_tables/create_characters.sql
pyneople/db/schema/staging_tables/staging_character_timelines.sql
pyneople/db/schema/staging_tables/staging_characters.sql
pyneople/db/utils/db_init.py
pyneople/db/utils/get_mongo_endpoints.py
pyneople/db/utils/get_mongo_split_filters.py
pyneople/db/utils/mongo_manager.py
pyneople/db/utils/psql_manager.py
pyneople/db/utils/query_builder.py
pyneople/utils/decorators.py
pyneople/utils/functions.py
pyneople/utils/logger_config.py
pyneople/utils/monitoring.py
pyneople/workers/__init__.py
pyneople/workers/api_fetch_worker.py
pyneople/workers/base_worker.py
pyneople/workers/mongo_router.py
pyneople/workers/mongo_store_worker.py
pyneople/workers/queue_to_psql_worker.py
pyneople/workers/shutdwon_controller.py
pyneople-1.0.3.dist-info/licenses/LICENSE
pyneople-1.0.3.dist-info/METADATA
pyneople-1.0.3.dist-info/WHEEL
pyneople-1.0.3.dist-info/top_level.txt
pyneople-1.0.3.dist-info/RECORD
